smarkets/__init__.py
smarkets/collections.py
smarkets/configuration.py
smarkets/datetime.py
smarkets/errors.py
smarkets/functools.py
smarkets/graphite.py
smarkets/greenlet.py
smarkets/hal_messenger_client.py
smarkets/interfaces.py
smarkets/itertools.py
smarkets/jinja.py
smarkets/lazy.py
smarkets/modules.py
smarkets/odds.py
smarkets/signal.py
smarkets/statsd.py
smarkets/string.py
smarkets/utils.py
smarkets/uuid.py
smarkets/streaming_api/__init__.py
smarkets/streaming_api/api.py
smarkets/streaming_api/client.py
smarkets/streaming_api/eto.py
smarkets/streaming_api/eto_pb2.py
smarkets/streaming_api/exceptions.py
smarkets/streaming_api/framing.py
smarkets/streaming_api/session.py
smarkets/streaming_api/seto.py
smarkets/streaming_api/seto_pb2.py
smarkets/streaming_api/utils.py
smarkets/tests/__init__.py
smarkets/tests/collections.py
smarkets/tests/datetime.py
smarkets/tests/errors.py
smarkets/tests/functools.py
smarkets/tests/greenlet.py
smarkets/tests/itertools.py
smarkets/tests/lazy.py
smarkets/tests/odds.py
smarkets/tests/signal.py
smarkets/tests/string.py
smarkets/tests/utils.py
smarkets/tests/uuid.py
smk_python_sdk-9.4.4.dist-info/LICENSE
smk_python_sdk-9.4.4.dist-info/METADATA
smk_python_sdk-9.4.4.dist-info/WHEEL
smk_python_sdk-9.4.4.dist-info/top_level.txt
smk_python_sdk-9.4.4.dist-info/RECORD
