Metadata-Version: 2.1
Name: smk-python-sdk
Version: 9.4.4
Summary: Smarkets Python SDK - API clients and utility library
Home-page: https://github.com/smarkets/smk_python_sdk
Author: Smarkets Limited
Author-email: support@smarkets.com
Maintainer: Smarkets Limited
Maintainer-email: support@smarkets.com
License: MIT
Download-URL: https://github.com/smarkets/smk_python_sdk/downloads/smk_python_sdk-9.4.4.tar.gz
Keywords: Smarkets,betting exchange
Platform: UNKNOWN
Classifier: Development Status :: 3 - Alpha
Classifier: Environment :: Console
Classifier: Intended Audience :: Developers
Classifier: License :: OSI Approved :: MIT License
Classifier: Operating System :: OS Independent
Classifier: Programming Language :: Python
Requires-Dist: decorator
Requires-Dist: iso8601
Requires-Dist: protobuf
Requires-Dist: pytz
Requires-Dist: six
